[
  {
    "slot": "08:00",
    "text": "【ランキング急上昇】\n即日出荷 カミオジャパン エクランウルーシール 金箔押し 立体 3D ストーン付 ぷっくり シェル アンティーク 魔法少女 エンジェル フラワー フルーツ くま うさぎ カラフル カワイイ かわいい 手紙 手帳 デコ コラージュ デコレーション 日記 手帳 手紙 シール集め シル活\nランキング：文房具・事務用品ランキング\n27位 → 2位（25ランク上昇）\n価格：¥418\nhttps://hb.afl.rakuten.co.jp/hgc/g00qvmsn.o0kuc366.g00qvmsn.o0kud42f/?pc=https%3A%2F%2Fitem.rakuten.co.jp%2Foroshi-ee%2Fkj-220635%2F&rafcid=wsc_i_ra_26577f62-6f86-4f06-adb3-9049f97517ab\n\n※広告",
    "itemCode": "oroshi-ee:10010943"
  },
  {
    "slot": "13:00",
    "text": "【ランキング急上昇】\nトモダチコレクション わくわく生活\nランキング：テレビゲーム総合ランキング / その他\n29位 → 8位（21ランク上昇）\n価格：¥6,557\nhttps://hb.afl.rakuten.co.jp/hgc/g00q072n.o0kucb4b.g00q072n.o0kud3bf/?pc=https%3A%2F%2Fitem.rakuten.co.jp%2Fbook%2F18522186%2F&rafcid=wsc_i_ra_26577f62-6f86-4f06-adb3-9049f97517ab\n\n※広告",
    "itemCode": "book:21864503"
  },
  {
    "slot": "20:00",
    "text": "【ランキング急上昇】\n【即納(営業日内の発送)】Nintendo Switch2 日本語 国内専用 ニンテンドー スイッチ2 本体 任天堂 新型 送料無料 任天堂switch2 BEE-S-KB6CA [ラッピング可] R-LOGI\nランキング：テレビゲーム総合ランキング / 本体・セット\n18位 → 3位（15ランク上昇）\n価格：¥56,289\nhttps://hb.afl.rakuten.co.jp/hgc/g00sxgsn.o0kucd1b.g00sxgsn.o0kud74e/?pc=https%3A%2F%2Fitem.rakuten.co.jp%2Fsokutei%2F4902370553024%2F&rafcid=wsc_i_ra_26577f62-6f86-4f06-adb3-9049f97517ab\n\n※広告",
    "itemCode": "sokutei:10191194"
  }
]
